twutils/NLO.py
twutils/__init__.py
twutils/plot.py
twutils/pre.py
twutils/QO/__init__.py
twutils/QO/ionization.py
twutils/QO/stationary.py
twutils/command_line/__init__.py
twutils/command_line/os2tw.py
twutils/command_line/twinstall.py
twutils/command_line/twplot.py
twutils/command_line/twscan.py
twutils/command_line/twtest.py
twutils/command_line/wigner.py
twutils-4.7.0.dist-info/LICENSE
twutils-4.7.0.dist-info/METADATA
twutils-4.7.0.dist-info/WHEEL
twutils-4.7.0.dist-info/entry_points.txt
twutils-4.7.0.dist-info/top_level.txt
twutils-4.7.0.dist-info/RECORD
