Metadata-Version: 2.1
Name: twutils
Version: 4.7.0
Summary: TurboWAVE utilities
Home-page: https://github.com/USNavalResearchLaboratory/turboWAVE
Author: Daniel Gordon
Author-email: daniel.gordon@nrl.navy.mil
License: PUBLIC-DOMAIN
Platform: UNKNOWN
Classifier: Programming Language :: Python :: 3
Requires-Python: >=3.8
License-File: LICENSE
Requires-Dist: scipy (>=1.5)
Requires-Dist: matplotlib (>=3.3)
Requires-Dist: jupyter (>=1)
Requires-Dist: ipympl (>=0.5)
Requires-Dist: pillow (>=8)
Requires-Dist: h5py
